{
  "meta": {
    "last_updated_at": "2024-11-05T23:59:59Z"
  },
  "data": {
    "ADA": {
      "code": "ADA",
      "value": 3.0035335635
    },
    "AED": {
      "code": "AED",
      "value": 3.6696904427
    },
    "AFN": {
      "code": "AFN",
      "value": 68.0772225274
    },
    "ALL": {
      "code": "ALL",
      "value": 89.5414309919
    },
    "AMD": {
      "code": "AMD",
      "value": 385.154914502
    },
    "ANG": {
      "code": "ANG",
      "value": 1.7839103208
    },
    "AOA": {
      "code": "AOA",
      "value": 904.7959704487
    },
    "ARB": {
      "code": "ARB",
      "value": 2.0420480866
    },
    "ARS": {
      "code": "ARS",
      "value": 991.1166466455
    },
    "AUD": {
      "code": "AUD",
      "value": 1.50524019
    },
    "AVAX": {
      "code": "AVAX",
      "value": 0.0417481293
    },
    "AWG": {
      "code": "AWG",
      "value": 1.79
    },
    "AZN": {
      "code": "AZN",
      "value": 1.7
    },
    "BAM": {
      "code": "BAM",
      "value": 1.7876201833
    },
    "BBD": {
      "code": "BBD",
      "value": 2
    },
    "BDT": {
      "code": "BDT",
      "value": 119.8057937766
    },
    "BGN": {
      "code": "BGN",
      "value": 1.7860802712
    },
    "BHD": {
      "code": "BHD",
      "value": 0.376
    },
    "BIF": {
      "code": "BIF",
      "value": 2894.2955960248
    },
    "BMD": {
      "code": "BMD",
      "value": 1
    },
    "BNB": {
      "code": "BNB",
      "value": 0.0017770275
    },
    "BND": {
      "code": "BND",
      "value": 1.3123301408
    },
    "BOB": {
      "code": "BOB",
      "value": 6.9155108687
    },
    "BRL": {
      "code": "BRL",
      "value": 5.7431406136
    },
    "BSD": {
      "code": "BSD",
      "value": 1
    },
    "BTC": {
      "code": "BTC",
      "value": 0.0000144237
    },
    "BTN": {
      "code": "BTN",
      "value": 83.9584118879
    },
    "BWP": {
      "code": "BWP",
      "value": 13.3218426571
    },
    "BYN": {
      "code": "BYN",
      "value": 3.2699383714
    },
    "BYR": {
      "code": "BYR",
      "value": 32699.396487346
    },
    "BZD": {
      "code": "BZD",
      "value": 2
    },
    "CAD": {
      "code": "CAD",
      "value": 1.3822901775
    },
    "CDF": {
      "code": "CDF",
      "value": 2845.0263693451
    },
    "CHF": {
      "code": "CHF",
      "value": 0.861990091
    },
    "CLF": {
      "code": "CLF",
      "value": 0.024750003
    },
    "CLP": {
      "code": "CLP",
      "value": 953.7892192917
    },
    "CNY": {
      "code": "CNY",
      "value": 7.093130926
    },
    "COP": {
      "code": "COP",
      "value": 4400.3011657149
    },
    "CRC": {
      "code": "CRC",
      "value": 512.2343553579
    },
    "CUC": {
      "code": "CUC",
      "value": 1
    },
    "CUP": {
      "code": "CUP",
      "value": 24
    },
    "CVE": {
      "code": "CVE",
      "value": 100.8393015152
    },
    "CZK": {
      "code": "CZK",
      "value": 23.0771837974
    },
    "DAI": {
      "code": "DAI",
      "value": 1.0020279653
    },
    "DJF": {
      "code": "DJF",
      "value": 177.721
    },
    "DKK": {
      "code": "DKK",
      "value": 6.8171009555
    },
    "DOP": {
      "code": "DOP",
      "value": 60.1066970668
    },
    "DOT": {
      "code": "DOT",
      "value": 0.2597865281
    },
    "DZD": {
      "code": "DZD",
      "value": 133.1777643537
    },
    "EGP": {
      "code": "EGP",
      "value": 49.1193996854
    },
    "ERN": {
      "code": "ERN",
      "value": 15
    },
    "ETB": {
      "code": "ETB",
      "value": 119.8287821518
    },
    "ETH": {
      "code": "ETH",
      "value": 0.0004129693
    },
    "EUR": {
      "code": "EUR",
      "value": 0.9142501502
    },
    "FJD": {
      "code": "FJD",
      "value": 2.2394603717
    },
    "FKP": {
      "code": "FKP",
      "value": 0.7667230969
    },
    "GBP": {
      "code": "GBP",
      "value": 0.7664801395
    },
    "GEL": {
      "code": "GEL",
      "value": 2.7088704249
    },
    "GGP": {
      "code": "GGP",
      "value": 0.7667230759
    },
    "GHS": {
      "code": "GHS",
      "value": 16.2484825118
    },
    "GIP": {
      "code": "GIP",
      "value": 0.7667233479
    },
    "GMD": {
      "code": "GMD",
      "value": 56.7761299829
    },
    "GNF": {
      "code": "GNF",
      "value": 8600.2607200681
    },
    "GTQ": {
      "code": "GTQ",
      "value": 7.7027914237
    },
    "GYD": {
      "code": "GYD",
      "value": 208.5930123263
    },
    "HKD": {
      "code": "HKD",
      "value": 7.7656409174
    },
    "HNL": {
      "code": "HNL",
      "value": 24.966474617
    },
    "HRK": {
      "code": "HRK",
      "value": 6.4886109044
    },
    "HTG": {
      "code": "HTG",
      "value": 133.2942537692
    },
    "HUF": {
      "code": "HUF",
      "value": 373.2032401039
    },
    "IDR": {
      "code": "IDR",
      "value": 15692.245869317
    },
    "ILS": {
      "code": "ILS",
      "value": 3.7491907144
    },
    "IMP": {
      "code": "IMP",
      "value": 0.7667231717
    },
    "INR": {
      "code": "INR",
      "value": 84.0373492604
    },
    "IQD": {
      "code": "IQD",
      "value": 1306.2002024274
    },
    "IRR": {
      "code": "IRR",
      "value": 41945.861286135
    },
    "ISK": {
      "code": "ISK",
      "value": 135.8382016173
    },
    "JEP": {
      "code": "JEP",
      "value": 0.7667228662
    },
    "JMD": {
      "code": "JMD",
      "value": 157.7280299378
    },
    "JOD": {
      "code": "JOD",
      "value": 0.71
    },
    "JPY": {
      "code": "JPY",
      "value": 151.3930974915
    },
    "KES": {
      "code": "KES",
      "value": 128.9968135581
    },
    "KGS": {
      "code": "KGS",
      "value": 85.7420010988
    },
    "KHR": {
      "code": "KHR",
      "value": 4052.2436900869
    },
    "KMF": {
      "code": "KMF",
      "value": 450.9401289382
    },
    "KPW": {
      "code": "KPW",
      "value": 900.0097018505
    },
    "KRW": {
      "code": "KRW",
      "value": 1374.723253708
    },
    "KWD": {
      "code": "KWD",
      "value": 0.3058200582
    },
    "KYD": {
      "code": "KYD",
      "value": 0.83333
    },
    "KZT": {
      "code": "KZT",
      "value": 487.9709488336
    },
    "LAK": {
      "code": "LAK",
      "value": 21754.08599684
    },
    "LBP": {
      "code": "LBP",
      "value": 89419.55674
    },
    "LKR": {
      "code": "LKR",
      "value": 291.4001578329
    },
    "LRD": {
      "code": "LRD",
      "value": 191.4775771354
    },
    "LSL": {
      "code": "LSL",
      "value": 17.3772732787
    },
    "LTC": {
      "code": "LTC",
      "value": 0.0153045945
    },
    "LTL": {
      "code": "LTL",
      "value": 3.1580597184
    },
    "LVL": {
      "code": "LVL",
      "value": 0.6428067316
    },
    "LYD": {
      "code": "LYD",
      "value": 4.8034306427
    },
    "MAD": {
      "code": "MAD",
      "value": 9.7765712005
    },
    "MATIC": {
      "code": "MATIC",
      "value": 3.1043904561
    },
    "MDL": {
      "code": "MDL",
      "value": 17.718812773
    },
    "MGA": {
      "code": "MGA",
      "value": 4602.3139924546
    },
    "MKD": {
      "code": "MKD",
      "value": 56.2960072139
    },
    "MMK": {
      "code": "MMK",
      "value": 2095.4957577093
    },
    "MNT": {
      "code": "MNT",
      "value": 3415.8789963625
    },
    "MOP": {
      "code": "MOP",
      "value": 7.9545812976
    },
    "MRO": {
      "code": "MRO",
      "value": 356.999828
    },
    "MRU": {
      "code": "MRU",
      "value": 39.798306297
    },
    "MUR": {
      "code": "MUR",
      "value": 45.8241559912
    },
    "MVR": {
      "code": "MVR",
      "value": 15.4296518823
    },
    "MWK": {
      "code": "MWK",
      "value": 1731.3345616706
    },
    "MXN": {
      "code": "MXN",
      "value": 20.1158122427
    },
    "MYR": {
      "code": "MYR",
      "value": 4.3432707995
    },
    "MZN": {
      "code": "MZN",
      "value": 63.4980591219
    },
    "NAD": {
      "code": "NAD",
      "value": 17.3558124852
    },
    "NGN": {
      "code": "NGN",
      "value": 1662.2980267754
    },
    "NIO": {
      "code": "NIO",
      "value": 36.7888906119
    },
    "NOK": {
      "code": "NOK",
      "value": 10.9387820805
    },
    "NPR": {
      "code": "NPR",
      "value": 133.8300349266
    },
    "NZD": {
      "code": "NZD",
      "value": 1.6615203104
    },
    "OMR": {
      "code": "OMR",
      "value": 0.3833700654
    },
    "OP": {
      "code": "OP",
      "value": 0.7072806696
    },
    "PAB": {
      "code": "PAB",
      "value": 0.9985001642
    },
    "PEN": {
      "code": "PEN",
      "value": 3.7724506507
    },
    "PGK": {
      "code": "PGK",
      "value": 3.9171604379
    },
    "PHP": {
      "code": "PHP",
      "value": 58.3966866073
    },
    "PKR": {
      "code": "PKR",
      "value": 277.3912626951
    },
    "PLN": {
      "code": "PLN",
      "value": 3.97344054
    },
    "PYG": {
      "code": "PYG",
      "value": 7802.4343289423
    },
    "QAR": {
      "code": "QAR",
      "value": 3.6346304559
    },
    "RON": {
      "code": "RON",
      "value": 4.5494507548
    },
    "RSD": {
      "code": "RSD",
      "value": 106.6108859447
    },
    "RUB": {
      "code": "RUB",
      "value": 97.4093204276
    },
    "RWF": {
      "code": "RWF",
      "value": 1356.1208808799
    },
    "SAR": {
      "code": "SAR",
      "value": 3.7437707429
    },
    "SBD": {
      "code": "SBD",
      "value": 8.3760454711
    },
    "SCR": {
      "code": "SCR",
      "value": 14.8789317865
    },
    "SDG": {
      "code": "SDG",
      "value": 601.5
    },
    "SEK": {
      "code": "SEK",
      "value": 10.6898318425
    },
    "SGD": {
      "code": "SGD",
      "value": 1.3126801883
    },
    "SHP": {
      "code": "SHP",
      "value": 0.7664801004
    },
    "SLL": {
      "code": "SLL",
      "value": 22562.644699004
    },
    "SOL": {
      "code": "SOL",
      "value": 0.0060097903
    },
    "SOS": {
      "code": "SOS",
      "value": 570.9904712967
    },
    "SRD": {
      "code": "SRD",
      "value": 34.6141236191
    },
    "STD": {
      "code": "STD",
      "value": 22668.998203376
    },
    "STN": {
      "code": "STN",
      "value": 22.6689863316
    },
    "SVC": {
      "code": "SVC",
      "value": 8.75
    },
    "SYP": {
      "code": "SYP",
      "value": 13002.866143467
    },
    "SZL": {
      "code": "SZL",
      "value": 17.3938217965
    },
    "THB": {
      "code": "THB",
      "value": 33.5340737879
    },
    "TJS": {
      "code": "TJS",
      "value": 10.5776216854
    },
    "TMT": {
      "code": "TMT",
      "value": 3.5
    },
    "TND": {
      "code": "TND",
      "value": 3.088890546
    },
    "TOP": {
      "code": "TOP",
      "value": 2.3460704363
    },
    "TRY": {
      "code": "TRY",
      "value": 34.2886761391
    },
    "TTD": {
      "code": "TTD",
      "value": 6.7186412301
    },
    "TWD": {
      "code": "TWD",
      "value": 31.8491344737
    },
    "TZS": {
      "code": "TZS",
      "value": 2688.3814280056
    },
    "UAH": {
      "code": "UAH",
      "value": 41.45761537
    },
    "UGX": {
      "code": "UGX",
      "value": 3663.9537825105
    },
    "USD": {
      "code": "USD",
      "value": 1
    },
    "USDC": {
      "code": "USDC",
      "value": 1.0032276073
    },
    "USDT": {
      "code": "USDT",
      "value": 1.0016713849
    },
    "UYU": {
      "code": "UYU",
      "value": 41.578104969
    },
    "UZS": {
      "code": "UZS",
      "value": 12773.040351595
    },
    "VEF": {
      "code": "VEF",
      "value": 4343926.5000249
    },
    "VES": {
      "code": "VES",
      "value": 43.4392821657
    },
    "VND": {
      "code": "VND",
      "value": 25290.766556968
    },
    "VUV": {
      "code": "VUV",
      "value": 120.3699934764
    },
    "WST": {
      "code": "WST",
      "value": 2.7576567049
    },
    "XAF": {
      "code": "XAF",
      "value": 599.717264943
    },
    "XAG": {
      "code": "XAG",
      "value": 0.0305756887
    },
    "XAU": {
      "code": "XAU",
      "value": 0.0003642175
    },
    "XCD": {
      "code": "XCD",
      "value": 2.7
    },
    "XDR": {
      "code": "XDR",
      "value": 0.7461901456
    },
    "XOF": {
      "code": "XOF",
      "value": 599.7172447636
    },
    "XPD": {
      "code": "XPD",
      "value": 0.0009279565
    },
    "XPF": {
      "code": "XPF",
      "value": 109.039087826
    },
    "XPT": {
      "code": "XPT",
      "value": 0.0009995398
    },
    "XRP": {
      "code": "XRP",
      "value": 1.9483312226
    },
    "YER": {
      "code": "YER",
      "value": 249.2431351586
    },
    "ZAR": {
      "code": "ZAR",
      "value": 17.3777319953
    },
    "ZMK": {
      "code": "ZMK",
      "value": 9001.2
    },
    "ZMW": {
      "code": "ZMW",
      "value": 27.0029238689
    },
    "ZWL": {
      "code": "ZWL",
      "value": 68445.477073206
    }
  }
}