{
  "meta": {
    "last_updated_at": "2024-07-18T23:59:59Z"
  },
  "data": {
    "ADA": {
      "code": "ADA",
      "value": 2.3563341832
    },
    "AED": {
      "code": "AED",
      "value": 3.6713506678
    },
    "AFN": {
      "code": "AFN",
      "value": 70.6251290531
    },
    "ALL": {
      "code": "ALL",
      "value": 91.9137299036
    },
    "AMD": {
      "code": "AMD",
      "value": 388.4797663144
    },
    "ANG": {
      "code": "ANG",
      "value": 1.7850802808
    },
    "AOA": {
      "code": "AOA",
      "value": 874.4287959336
    },
    "ARB": {
      "code": "ARB",
      "value": 1.3346917598
    },
    "ARS": {
      "code": "ARS",
      "value": 923.8698453725
    },
    "AUD": {
      "code": "AUD",
      "value": 1.4909502025
    },
    "AVAX": {
      "code": "AVAX",
      "value": 0.0367810931
    },
    "AWG": {
      "code": "AWG",
      "value": 1.79
    },
    "AZN": {
      "code": "AZN",
      "value": 1.7
    },
    "BAM": {
      "code": "BAM",
      "value": 1.7930902779
    },
    "BBD": {
      "code": "BBD",
      "value": 2
    },
    "BDT": {
      "code": "BDT",
      "value": 117.8162498775
    },
    "BGN": {
      "code": "BGN",
      "value": 1.7894602475
    },
    "BHD": {
      "code": "BHD",
      "value": 0.376
    },
    "BIF": {
      "code": "BIF",
      "value": 2878.3741876618
    },
    "BMD": {
      "code": "BMD",
      "value": 1
    },
    "BNB": {
      "code": "BNB",
      "value": 0.0017312129
    },
    "BND": {
      "code": "BND",
      "value": 1.3424201546
    },
    "BOB": {
      "code": "BOB",
      "value": 6.907120698
    },
    "BRL": {
      "code": "BRL",
      "value": 5.5438708615
    },
    "BSD": {
      "code": "BSD",
      "value": 1
    },
    "BTC": {
      "code": "BTC",
      "value": 0.0000156008
    },
    "BTN": {
      "code": "BTN",
      "value": 83.744072986
    },
    "BWP": {
      "code": "BWP",
      "value": 13.5577616488
    },
    "BYN": {
      "code": "BYN",
      "value": 3.2700802495
    },
    "BYR": {
      "code": "BYR",
      "value": 32700.799685779
    },
    "BZD": {
      "code": "BZD",
      "value": 2
    },
    "CAD": {
      "code": "CAD",
      "value": 1.369800242
    },
    "CDF": {
      "code": "CDF",
      "value": 2827.473951644
    },
    "CHF": {
      "code": "CHF",
      "value": 0.8871801264
    },
    "CLF": {
      "code": "CLF",
      "value": 0.0246300032
    },
    "CLP": {
      "code": "CLP",
      "value": 941.6498652731
    },
    "CNY": {
      "code": "CNY",
      "value": 7.2539614396
    },
    "COP": {
      "code": "COP",
      "value": 4046.2530266155
    },
    "CRC": {
      "code": "CRC",
      "value": 520.5703461246
    },
    "CUC": {
      "code": "CUC",
      "value": 1
    },
    "CUP": {
      "code": "CUP",
      "value": 24
    },
    "CVE": {
      "code": "CVE",
      "value": 101.1194665561
    },
    "CZK": {
      "code": "CZK",
      "value": 23.1468942141
    },
    "DAI": {
      "code": "DAI",
      "value": 0.9978000965
    },
    "DJF": {
      "code": "DJF",
      "value": 177.721
    },
    "DKK": {
      "code": "DKK",
      "value": 6.8418309448
    },
    "DOP": {
      "code": "DOP",
      "value": 59.1035210241
    },
    "DOT": {
      "code": "DOT",
      "value": 0.1638275136
    },
    "DZD": {
      "code": "DZD",
      "value": 134.8372843707
    },
    "EGP": {
      "code": "EGP",
      "value": 48.2093469168
    },
    "ERN": {
      "code": "ERN",
      "value": 15
    },
    "ETB": {
      "code": "ETB",
      "value": 57.9538094401
    },
    "ETH": {
      "code": "ETH",
      "value": 0.0002912268
    },
    "EUR": {
      "code": "EUR",
      "value": 0.9170101641
    },
    "FJD": {
      "code": "FJD",
      "value": 2.2326703668
    },
    "FKP": {
      "code": "FKP",
      "value": 0.7721736271
    },
    "GBP": {
      "code": "GBP",
      "value": 0.77203009
    },
    "GEL": {
      "code": "GEL",
      "value": 2.7070402947
    },
    "GGP": {
      "code": "GGP",
      "value": 0.7721734436
    },
    "GHS": {
      "code": "GHS",
      "value": 15.372272943
    },
    "GIP": {
      "code": "GIP",
      "value": 0.7721737363
    },
    "GMD": {
      "code": "GMD",
      "value": 57.187716739
    },
    "GNF": {
      "code": "GNF",
      "value": 8588.6461214635
    },
    "GTQ": {
      "code": "GTQ",
      "value": 7.7419614204
    },
    "GYD": {
      "code": "GYD",
      "value": 208.7633898031
    },
    "HKD": {
      "code": "HKD",
      "value": 7.8068107885
    },
    "HNL": {
      "code": "HNL",
      "value": 24.7430730318
    },
    "HRK": {
      "code": "HRK",
      "value": 6.5356406905
    },
    "HTG": {
      "code": "HTG",
      "value": 134.0968963264
    },
    "HUF": {
      "code": "HUF",
      "value": 358.2245285016
    },
    "IDR": {
      "code": "IDR",
      "value": 16122.694779065
    },
    "ILS": {
      "code": "ILS",
      "value": 3.6516205831
    },
    "IMP": {
      "code": "IMP",
      "value": 0.7721736104
    },
    "INR": {
      "code": "INR",
      "value": 83.5170896323
    },
    "IQD": {
      "code": "IQD",
      "value": 1307.1847343578
    },
    "IRR": {
      "code": "IRR",
      "value": 41978.727497536
    },
    "ISK": {
      "code": "ISK",
      "value": 136.9279393247
    },
    "JEP": {
      "code": "JEP",
      "value": 0.7721736493
    },
    "JMD": {
      "code": "JMD",
      "value": 155.7825527634
    },
    "JOD": {
      "code": "JOD",
      "value": 0.71
    },
    "JPY": {
      "code": "JPY",
      "value": 157.1189372154
    },
    "KES": {
      "code": "KES",
      "value": 130.9639585414
    },
    "KGS": {
      "code": "KGS",
      "value": 85.0094338677
    },
    "KHR": {
      "code": "KHR",
      "value": 4099.7472186662
    },
    "KMF": {
      "code": "KMF",
      "value": 450.2980716379
    },
    "KPW": {
      "code": "KPW",
      "value": 899.9706297711
    },
    "KRW": {
      "code": "KRW",
      "value": 1380.5588782207
    },
    "KWD": {
      "code": "KWD",
      "value": 0.3052300381
    },
    "KYD": {
      "code": "KYD",
      "value": 0.83333
    },
    "KZT": {
      "code": "KZT",
      "value": 478.1299186044
    },
    "LAK": {
      "code": "LAK",
      "value": 22144.94392983
    },
    "LBP": {
      "code": "LBP",
      "value": 89494.178766717
    },
    "LKR": {
      "code": "LKR",
      "value": 304.7009533371
    },
    "LRD": {
      "code": "LRD",
      "value": 195.8719634908
    },
    "LSL": {
      "code": "LSL",
      "value": 18.2343621367
    },
    "LTC": {
      "code": "LTC",
      "value": 0.0139453583
    },
    "LTL": {
      "code": "LTL",
      "value": 3.1672176835
    },
    "LVL": {
      "code": "LVL",
      "value": 0.6446705927
    },
    "LYD": {
      "code": "LYD",
      "value": 4.8159506159
    },
    "MAD": {
      "code": "MAD",
      "value": 9.8001211985
    },
    "MATIC": {
      "code": "MATIC",
      "value": 1.9317258189
    },
    "MDL": {
      "code": "MDL",
      "value": 17.5386824048
    },
    "MGA": {
      "code": "MGA",
      "value": 4509.2881870215
    },
    "MKD": {
      "code": "MKD",
      "value": 56.478147742
    },
    "MMK": {
      "code": "MMK",
      "value": 2093.5321114452
    },
    "MNT": {
      "code": "MNT",
      "value": 3401.3533566681
    },
    "MOP": {
      "code": "MOP",
      "value": 8.0568709158
    },
    "MRO": {
      "code": "MRO",
      "value": 356.999828
    },
    "MRU": {
      "code": "MRU",
      "value": 39.5377339821
    },
    "MUR": {
      "code": "MUR",
      "value": 46.4135991697
    },
    "MVR": {
      "code": "MVR",
      "value": 15.4403729037
    },
    "MWK": {
      "code": "MWK",
      "value": 1732.4055821101
    },
    "MXN": {
      "code": "MXN",
      "value": 17.9484730916
    },
    "MYR": {
      "code": "MYR",
      "value": 4.6630807941
    },
    "MZN": {
      "code": "MZN",
      "value": 63.5338415484
    },
    "NAD": {
      "code": "NAD",
      "value": 18.2072629718
    },
    "NGN": {
      "code": "NGN",
      "value": 1572.5790652279
    },
    "NIO": {
      "code": "NIO",
      "value": 36.7962011881
    },
    "NOK": {
      "code": "NOK",
      "value": 10.8080918686
    },
    "NPR": {
      "code": "NPR",
      "value": 134.0706544205
    },
    "NZD": {
      "code": "NZD",
      "value": 1.6543902375
    },
    "OMR": {
      "code": "OMR",
      "value": 0.3838200757
    },
    "OP": {
      "code": "OP",
      "value": 0.5471062008
    },
    "PAB": {
      "code": "PAB",
      "value": 0.9987301451
    },
    "PEN": {
      "code": "PEN",
      "value": 3.7329007158
    },
    "PGK": {
      "code": "PGK",
      "value": 3.8803205341
    },
    "PHP": {
      "code": "PHP",
      "value": 58.3182911746
    },
    "PKR": {
      "code": "PKR",
      "value": 277.8673849575
    },
    "PLN": {
      "code": "PLN",
      "value": 3.9340505125
    },
    "PYG": {
      "code": "PYG",
      "value": 7573.0197340352
    },
    "QAR": {
      "code": "QAR",
      "value": 3.6372007253
    },
    "RON": {
      "code": "RON",
      "value": 4.556020895
    },
    "RSD": {
      "code": "RSD",
      "value": 106.946008349
    },
    "RUB": {
      "code": "RUB",
      "value": 88.3314946987
    },
    "RWF": {
      "code": "RWF",
      "value": 1309.0838972214
    },
    "SAR": {
      "code": "SAR",
      "value": 3.7416005332
    },
    "SBD": {
      "code": "SBD",
      "value": 8.3281378793
    },
    "SCR": {
      "code": "SCR",
      "value": 14.8386418668
    },
    "SDG": {
      "code": "SDG",
      "value": 601.5
    },
    "SEK": {
      "code": "SEK",
      "value": 10.5903714024
    },
    "SGD": {
      "code": "SGD",
      "value": 1.3434201983
    },
    "SHP": {
      "code": "SHP",
      "value": 0.7720301481
    },
    "SLL": {
      "code": "SLL",
      "value": 22463.40969857
    },
    "SOL": {
      "code": "SOL",
      "value": 0.0062711799
    },
    "SOS": {
      "code": "SOS",
      "value": 571.5398103862
    },
    "SRD": {
      "code": "SRD",
      "value": 28.7103945046
    },
    "STD": {
      "code": "STD",
      "value": 22659.184241113
    },
    "STN": {
      "code": "STN",
      "value": 22.6592043306
    },
    "SVC": {
      "code": "SVC",
      "value": 8.75
    },
    "SYP": {
      "code": "SYP",
      "value": 13001.87264572
    },
    "SZL": {
      "code": "SZL",
      "value": 18.2400727994
    },
    "THB": {
      "code": "THB",
      "value": 36.1313446416
    },
    "TJS": {
      "code": "TJS",
      "value": 10.7014711827
    },
    "TMT": {
      "code": "TMT",
      "value": 3.5
    },
    "TND": {
      "code": "TND",
      "value": 3.0882904094
    },
    "TOP": {
      "code": "TOP",
      "value": 2.3409902687
    },
    "TRY": {
      "code": "TRY",
      "value": 33.0752451467
    },
    "TTD": {
      "code": "TTD",
      "value": 6.7758807816
    },
    "TWD": {
      "code": "TWD",
      "value": 32.6546435932
    },
    "TZS": {
      "code": "TZS",
      "value": 2685.2731146318
    },
    "UAH": {
      "code": "UAH",
      "value": 41.5531869676
    },
    "UGX": {
      "code": "UGX",
      "value": 3687.9057974023
    },
    "USD": {
      "code": "USD",
      "value": 1
    },
    "USDC": {
      "code": "USDC",
      "value": 0.9973379915
    },
    "USDT": {
      "code": "USDT",
      "value": 0.9980247198
    },
    "UYU": {
      "code": "UYU",
      "value": 40.3027162705
    },
    "UZS": {
      "code": "UZS",
      "value": 12622.292375588
    },
    "VEF": {
      "code": "VEF",
      "value": 3652654.9315732
    },
    "VES": {
      "code": "VES",
      "value": 36.5265395155
    },
    "VND": {
      "code": "VND",
      "value": 25285.811830152
    },
    "VUV": {
      "code": "VUV",
      "value": 118.8941206683
    },
    "WST": {
      "code": "WST",
      "value": 2.7357620267
    },
    "XAF": {
      "code": "XAF",
      "value": 601.5217585952
    },
    "XAG": {
      "code": "XAG",
      "value": 0.0335690126
    },
    "XAU": {
      "code": "XAU",
      "value": 0.0004094309
    },
    "XCD": {
      "code": "XCD",
      "value": 2.7
    },
    "XDR": {
      "code": "XDR",
      "value": 0.7547700808
    },
    "XOF": {
      "code": "XOF",
      "value": 601.521759618
    },
    "XPD": {
      "code": "XPD",
      "value": 0.0010744322
    },
    "XPF": {
      "code": "XPF",
      "value": 109.3555291403
    },
    "XPT": {
      "code": "XPT",
      "value": 0.0010307196
    },
    "XRP": {
      "code": "XRP",
      "value": 1.7506224733
    },
    "YER": {
      "code": "YER",
      "value": 249.6757983277
    },
    "ZAR": {
      "code": "ZAR",
      "value": 18.242161868
    },
    "ZMK": {
      "code": "ZMK",
      "value": 9001.2
    },
    "ZMW": {
      "code": "ZMW",
      "value": 26.1745028042
    },
    "ZWL": {
      "code": "ZWL",
      "value": 34765.490321174
    }
  }
}