{
  "meta": {
    "last_updated_at": "2024-10-28T23:59:59Z"
  },
  "data": {
    "ADA": {
      "code": "ADA",
      "value": 2.9119819887
    },
    "AED": {
      "code": "AED",
      "value": 3.6724004036
    },
    "AFN": {
      "code": "AFN",
      "value": 67.5287579217
    },
    "ALL": {
      "code": "ALL",
      "value": 91.0047619043
    },
    "AMD": {
      "code": "AMD",
      "value": 387.3030836617
    },
    "ANG": {
      "code": "ANG",
      "value": 1.7867803147
    },
    "AOA": {
      "code": "AOA",
      "value": 910.1324374045
    },
    "ARB": {
      "code": "ARB",
      "value": 1.9153652822
    },
    "ARS": {
      "code": "ARS",
      "value": 987.4041870993
    },
    "AUD": {
      "code": "AUD",
      "value": 1.5191602517
    },
    "AVAX": {
      "code": "AVAX",
      "value": 0.0381075965
    },
    "AWG": {
      "code": "AWG",
      "value": 1.79
    },
    "AZN": {
      "code": "AZN",
      "value": 1.7
    },
    "BAM": {
      "code": "BAM",
      "value": 1.807290294
    },
    "BBD": {
      "code": "BBD",
      "value": 2
    },
    "BDT": {
      "code": "BDT",
      "value": 120.0132745324
    },
    "BGN": {
      "code": "BGN",
      "value": 1.8066402063
    },
    "BHD": {
      "code": "BHD",
      "value": 0.376
    },
    "BIF": {
      "code": "BIF",
      "value": 2897.652469225
    },
    "BMD": {
      "code": "BMD",
      "value": 1
    },
    "BNB": {
      "code": "BNB",
      "value": 0.0016667223
    },
    "BND": {
      "code": "BND",
      "value": 1.3218802228
    },
    "BOB": {
      "code": "BOB",
      "value": 6.9095311297
    },
    "BRL": {
      "code": "BRL",
      "value": 5.6984107727
    },
    "BSD": {
      "code": "BSD",
      "value": 1
    },
    "BTC": {
      "code": "BTC",
      "value": 0.0000143058
    },
    "BTN": {
      "code": "BTN",
      "value": 84.2527338637
    },
    "BWP": {
      "code": "BWP",
      "value": 13.4140925973
    },
    "BYN": {
      "code": "BYN",
      "value": 3.2700252461
    },
    "BYR": {
      "code": "BYR",
      "value": 32700.230926716
    },
    "BZD": {
      "code": "BZD",
      "value": 2
    },
    "CAD": {
      "code": "CAD",
      "value": 1.3891202747
    },
    "CDF": {
      "code": "CDF",
      "value": 2840.8624466583
    },
    "CHF": {
      "code": "CHF",
      "value": 0.8647800928
    },
    "CLF": {
      "code": "CLF",
      "value": 0.0245900047
    },
    "CLP": {
      "code": "CLP",
      "value": 947.4809844659
    },
    "CNY": {
      "code": "CNY",
      "value": 7.1272709366
    },
    "COP": {
      "code": "COP",
      "value": 4334.3722076458
    },
    "CRC": {
      "code": "CRC",
      "value": 514.276656542
    },
    "CUC": {
      "code": "CUC",
      "value": 1
    },
    "CUP": {
      "code": "CUP",
      "value": 24
    },
    "CVE": {
      "code": "CVE",
      "value": 101.9418272757
    },
    "CZK": {
      "code": "CZK",
      "value": 23.4290541146
    },
    "DAI": {
      "code": "DAI",
      "value": 1.0004254386
    },
    "DJF": {
      "code": "DJF",
      "value": 177.721
    },
    "DKK": {
      "code": "DKK",
      "value": 6.8937707588
    },
    "DOP": {
      "code": "DOP",
      "value": 60.1318298193
    },
    "DOT": {
      "code": "DOT",
      "value": 0.2423170641
    },
    "DZD": {
      "code": "DZD",
      "value": 134.0160864672
    },
    "EGP": {
      "code": "EGP",
      "value": 48.7189094829
    },
    "ERN": {
      "code": "ERN",
      "value": 15
    },
    "ETB": {
      "code": "ETB",
      "value": 122.1794170065
    },
    "ETH": {
      "code": "ETH",
      "value": 0.0003898507
    },
    "EUR": {
      "code": "EUR",
      "value": 0.9244401022
    },
    "FJD": {
      "code": "FJD",
      "value": 2.2755903364
    },
    "FKP": {
      "code": "FKP",
      "value": 0.7708428106
    },
    "GBP": {
      "code": "GBP",
      "value": 0.7708700839
    },
    "GEL": {
      "code": "GEL",
      "value": 2.7226603844
    },
    "GGP": {
      "code": "GGP",
      "value": 0.7708433353
    },
    "GHS": {
      "code": "GHS",
      "value": 16.2549023485
    },
    "GIP": {
      "code": "GIP",
      "value": 0.7708426718
    },
    "GMD": {
      "code": "GMD",
      "value": 57.1013184959
    },
    "GNF": {
      "code": "GNF",
      "value": 8625.0818617318
    },
    "GTQ": {
      "code": "GTQ",
      "value": 7.7189312314
    },
    "GYD": {
      "code": "GYD",
      "value": 208.9421015931
    },
    "HKD": {
      "code": "HKD",
      "value": 7.7695713657
    },
    "HNL": {
      "code": "HNL",
      "value": 24.9665432547
    },
    "HRK": {
      "code": "HRK",
      "value": 6.5257712192
    },
    "HTG": {
      "code": "HTG",
      "value": 133.4749392315
    },
    "HUF": {
      "code": "HUF",
      "value": 373.2070286741
    },
    "IDR": {
      "code": "IDR",
      "value": 15711.897977591
    },
    "ILS": {
      "code": "ILS",
      "value": 3.7268005189
    },
    "IMP": {
      "code": "IMP",
      "value": 0.7708431009
    },
    "INR": {
      "code": "INR",
      "value": 84.0237813855
    },
    "IQD": {
      "code": "IQD",
      "value": 1308.069653816
    },
    "IRR": {
      "code": "IRR",
      "value": 42011.124309737
    },
    "ISK": {
      "code": "ISK",
      "value": 137.5728730787
    },
    "JEP": {
      "code": "JEP",
      "value": 0.7708430154
    },
    "JMD": {
      "code": "JMD",
      "value": 157.7919606499
    },
    "JOD": {
      "code": "JOD",
      "value": 0.71
    },
    "JPY": {
      "code": "JPY",
      "value": 153.2006564689
    },
    "KES": {
      "code": "KES",
      "value": 128.9953997753
    },
    "KGS": {
      "code": "KGS",
      "value": 85.7736551679
    },
    "KHR": {
      "code": "KHR",
      "value": 4066.3647040839
    },
    "KMF": {
      "code": "KMF",
      "value": 455.3259917274
    },
    "KPW": {
      "code": "KPW",
      "value": 899.9921752296
    },
    "KRW": {
      "code": "KRW",
      "value": 1379.0434162822
    },
    "KWD": {
      "code": "KWD",
      "value": 0.3058500443
    },
    "KYD": {
      "code": "KYD",
      "value": 0.83333
    },
    "KZT": {
      "code": "KZT",
      "value": 490.2879367482
    },
    "LAK": {
      "code": "LAK",
      "value": 21929.869334303
    },
    "LBP": {
      "code": "LBP",
      "value": 89571.717477225
    },
    "LKR": {
      "code": "LKR",
      "value": 293.2264459102
    },
    "LRD": {
      "code": "LRD",
      "value": 192.0600954137
    },
    "LSL": {
      "code": "LSL",
      "value": 17.6870919818
    },
    "LTC": {
      "code": "LTC",
      "value": 0.0141433496
    },
    "LTL": {
      "code": "LTL",
      "value": 3.1922671259
    },
    "LVL": {
      "code": "LVL",
      "value": 0.6497699432
    },
    "LYD": {
      "code": "LYD",
      "value": 4.8285908112
    },
    "MAD": {
      "code": "MAD",
      "value": 9.8325715812
    },
    "MATIC": {
      "code": "MATIC",
      "value": 2.9686856214
    },
    "MDL": {
      "code": "MDL",
      "value": 17.826921868
    },
    "MGA": {
      "code": "MGA",
      "value": 4609.186390916
    },
    "MKD": {
      "code": "MKD",
      "value": 56.7575104607
    },
    "MMK": {
      "code": "MMK",
      "value": 2098.9180743778
    },
    "MNT": {
      "code": "MNT",
      "value": 3417.5992299666
    },
    "MOP": {
      "code": "MOP",
      "value": 7.9942808267
    },
    "MRO": {
      "code": "MRO",
      "value": 356.999828
    },
    "MRU": {
      "code": "MRU",
      "value": 39.9670295336
    },
    "MUR": {
      "code": "MUR",
      "value": 46.2495874311
    },
    "MVR": {
      "code": "MVR",
      "value": 15.3410330438
    },
    "MWK": {
      "code": "MWK",
      "value": 1734.128094636
    },
    "MXN": {
      "code": "MXN",
      "value": 20.0122639994
    },
    "MYR": {
      "code": "MYR",
      "value": 4.3602708003
    },
    "MZN": {
      "code": "MZN",
      "value": 63.6034314056
    },
    "NAD": {
      "code": "NAD",
      "value": 17.6637325443
    },
    "NGN": {
      "code": "NGN",
      "value": 1637.6462895209
    },
    "NIO": {
      "code": "NIO",
      "value": 36.8040780777
    },
    "NOK": {
      "code": "NOK",
      "value": 10.987561547
    },
    "NPR": {
      "code": "NPR",
      "value": 134.359121166
    },
    "NZD": {
      "code": "NZD",
      "value": 1.6703402685
    },
    "OMR": {
      "code": "OMR",
      "value": 0.3840000522
    },
    "OP": {
      "code": "OP",
      "value": 0.6184866409
    },
    "PAB": {
      "code": "PAB",
      "value": 0.9991101769
    },
    "PEN": {
      "code": "PEN",
      "value": 3.774550664
    },
    "PGK": {
      "code": "PGK",
      "value": 3.9517404555
    },
    "PHP": {
      "code": "PHP",
      "value": 58.2276316349
    },
    "PKR": {
      "code": "PKR",
      "value": 277.6379431949
    },
    "PLN": {
      "code": "PLN",
      "value": 4.0192505512
    },
    "PYG": {
      "code": "PYG",
      "value": 7997.7506492356
    },
    "QAR": {
      "code": "QAR",
      "value": 3.6390404198
    },
    "RON": {
      "code": "RON",
      "value": 4.5969305827
    },
    "RSD": {
      "code": "RSD",
      "value": 108.0987457651
    },
    "RUB": {
      "code": "RUB",
      "value": 97.1986860301
    },
    "RWF": {
      "code": "RWF",
      "value": 1354.7302790672
    },
    "SAR": {
      "code": "SAR",
      "value": 3.7499104436
    },
    "SBD": {
      "code": "SBD",
      "value": 8.344857595
    },
    "SCR": {
      "code": "SCR",
      "value": 14.7859324957
    },
    "SDG": {
      "code": "SDG",
      "value": 601.5
    },
    "SEK": {
      "code": "SEK",
      "value": 10.6432916641
    },
    "SGD": {
      "code": "SGD",
      "value": 1.3221801646
    },
    "SHP": {
      "code": "SHP",
      "value": 0.770870122
    },
    "SLL": {
      "code": "SLL",
      "value": 22662.887332838
    },
    "SOL": {
      "code": "SOL",
      "value": 0.0056195708
    },
    "SOS": {
      "code": "SOS",
      "value": 571.0686713531
    },
    "SRD": {
      "code": "SRD",
      "value": 34.0356439052
    },
    "STD": {
      "code": "STD",
      "value": 22853.485630377
    },
    "STN": {
      "code": "STN",
      "value": 22.8534939669
    },
    "SVC": {
      "code": "SVC",
      "value": 8.75
    },
    "SYP": {
      "code": "SYP",
      "value": 13022.287447259
    },
    "SZL": {
      "code": "SZL",
      "value": 17.696732694
    },
    "THB": {
      "code": "THB",
      "value": 33.7672352465
    },
    "TJS": {
      "code": "TJS",
      "value": 10.6388914327
    },
    "TMT": {
      "code": "TMT",
      "value": 3.5
    },
    "TND": {
      "code": "TND",
      "value": 3.0987303867
    },
    "TOP": {
      "code": "TOP",
      "value": 2.3517303631
    },
    "TRY": {
      "code": "TRY",
      "value": 34.2822534638
    },
    "TTD": {
      "code": "TTD",
      "value": 6.7677811947
    },
    "TWD": {
      "code": "TWD",
      "value": 32.0631540221
    },
    "TZS": {
      "code": "TZS",
      "value": 2718.0556026517
    },
    "UAH": {
      "code": "UAH",
      "value": 41.4564077387
    },
    "UGX": {
      "code": "UGX",
      "value": 3666.0685847662
    },
    "USD": {
      "code": "USD",
      "value": 1
    },
    "USDC": {
      "code": "USDC",
      "value": 1.0012623199
    },
    "USDT": {
      "code": "USDT",
      "value": 1.0011784005
    },
    "UYU": {
      "code": "UYU",
      "value": 41.663846623
    },
    "UZS": {
      "code": "UZS",
      "value": 12814.515231471
    },
    "VEF": {
      "code": "VEF",
      "value": 4147449.9529065
    },
    "VES": {
      "code": "VES",
      "value": 41.4744864119
    },
    "VND": {
      "code": "VND",
      "value": 25346.972456765
    },
    "VUV": {
      "code": "VUV",
      "value": 120.4277792453
    },
    "WST": {
      "code": "WST",
      "value": 2.7592839162
    },
    "XAF": {
      "code": "XAF",
      "value": 606.4098803552
    },
    "XAG": {
      "code": "XAG",
      "value": 0.029672301
    },
    "XAU": {
      "code": "XAU",
      "value": 0.0003644622
    },
    "XCD": {
      "code": "XCD",
      "value": 2.7
    },
    "XDR": {
      "code": "XDR",
      "value": 0.753040115
    },
    "XOF": {
      "code": "XOF",
      "value": 606.4098568281
    },
    "XPD": {
      "code": "XPD",
      "value": 0.0008235347
    },
    "XPF": {
      "code": "XPF",
      "value": 110.2487019316
    },
    "XPT": {
      "code": "XPT",
      "value": 0.000966599
    },
    "XRP": {
      "code": "XRP",
      "value": 1.9259829775
    },
    "YER": {
      "code": "YER",
      "value": 249.9930986397
    },
    "ZAR": {
      "code": "ZAR",
      "value": 17.7024331723
    },
    "ZMK": {
      "code": "ZMK",
      "value": 9001.2
    },
    "ZMW": {
      "code": "ZMW",
      "value": 26.7041627871
    },
    "ZWL": {
      "code": "ZWL",
      "value": 70847.99889346
    }
  }
}