{
  "meta": {
    "last_updated_at": "2026-04-03T23:59:59Z"
  },
  "data": {
    "ADA": {
      "code": "ADA",
      "value": 4.0547769753
    },
    "AED": {
      "code": "AED",
      "value": 3.673400543
    },
    "AFN": {
      "code": "AFN",
      "value": 64.887212667
    },
    "ALL": {
      "code": "ALL",
      "value": 83.0700157683
    },
    "AMD": {
      "code": "AMD",
      "value": 376.9800679637
    },
    "ANG": {
      "code": "ANG",
      "value": 1.7880001961
    },
    "AOA": {
      "code": "AOA",
      "value": 912.1311083612
    },
    "ARB": {
      "code": "ARB",
      "value": 10.764420245
    },
    "ARS": {
      "code": "ARS",
      "value": 1386.2532650524
    },
    "AUD": {
      "code": "AUD",
      "value": 1.4504002229
    },
    "AVAX": {
      "code": "AVAX",
      "value": 0.1120829537
    },
    "AWG": {
      "code": "AWG",
      "value": 1.79
    },
    "AZN": {
      "code": "AZN",
      "value": 1.7
    },
    "BAM": {
      "code": "BAM",
      "value": 1.6980003299
    },
    "BBD": {
      "code": "BBD",
      "value": 2
    },
    "BDT": {
      "code": "BDT",
      "value": 122.7000126646
    },
    "BGN": {
      "code": "BGN",
      "value": 1.6650001778
    },
    "BHD": {
      "code": "BHD",
      "value": 0.376
    },
    "BIF": {
      "code": "BIF",
      "value": 2971.8604048075
    },
    "BMD": {
      "code": "BMD",
      "value": 1
    },
    "BNB": {
      "code": "BNB",
      "value": 0.0016974001
    },
    "BND": {
      "code": "BND",
      "value": 1.2868001371
    },
    "BOB": {
      "code": "BOB",
      "value": 6.9300013168
    },
    "BRL": {
      "code": "BRL",
      "value": 5.1594008141
    },
    "BSD": {
      "code": "BSD",
      "value": 1
    },
    "BTC": {
      "code": "BTC",
      "value": 0.0000149312
    },
    "BTN": {
      "code": "BTN",
      "value": 92.7743729845
    },
    "BWP": {
      "code": "BWP",
      "value": 13.3690017206
    },
    "BYN": {
      "code": "BYN",
      "value": 2.9500029712
    },
    "BYR": {
      "code": "BYR",
      "value": 29500.02941297
    },
    "BZD": {
      "code": "BZD",
      "value": 2
    },
    "CAD": {
      "code": "CAD",
      "value": 1.3946001773
    },
    "CDF": {
      "code": "CDF",
      "value": 2301.8202649673
    },
    "CHF": {
      "code": "CHF",
      "value": 0.8005301223
    },
    "CLF": {
      "code": "CLF",
      "value": 0.0230900036
    },
    "CLP": {
      "code": "CLP",
      "value": 919.8701402355
    },
    "CNY": {
      "code": "CNY",
      "value": 6.8824010776
    },
    "COP": {
      "code": "COP",
      "value": 3666.8706104494
    },
    "CRC": {
      "code": "CRC",
      "value": 464.6379568922
    },
    "CUC": {
      "code": "CUC",
      "value": 1
    },
    "CUP": {
      "code": "CUP",
      "value": 24
    },
    "CVE": {
      "code": "CVE",
      "value": 95.7100095795
    },
    "CZK": {
      "code": "CZK",
      "value": 21.2947032778
    },
    "DAI": {
      "code": "DAI",
      "value": 0.9992754207
    },
    "DJF": {
      "code": "DJF",
      "value": 177.721
    },
    "DKK": {
      "code": "DKK",
      "value": 6.487750883
    },
    "DOP": {
      "code": "DOP",
      "value": 60.7000109639
    },
    "DOT": {
      "code": "DOT",
      "value": 0.8069501518
    },
    "DZD": {
      "code": "DZD",
      "value": 133.4650212181
    },
    "EGP": {
      "code": "EGP",
      "value": 54.4000056357
    },
    "ERN": {
      "code": "ERN",
      "value": 15
    },
    "ETB": {
      "code": "ETB",
      "value": 155.8010251488
    },
    "ETH": {
      "code": "ETH",
      "value": 0.0004870282
    },
    "EUR": {
      "code": "EUR",
      "value": 0.8681691573
    },
    "FJD": {
      "code": "FJD",
      "value": 2.2538004231
    },
    "FKP": {
      "code": "FKP",
      "value": 0.7576037073
    },
    "GBP": {
      "code": "GBP",
      "value": 0.7579500982
    },
    "GEL": {
      "code": "GEL",
      "value": 2.6989005088
    },
    "GGP": {
      "code": "GGP",
      "value": 0.7576037589
    },
    "GHS": {
      "code": "GHS",
      "value": 10.9727019999
    },
    "GIP": {
      "code": "GIP",
      "value": 0.7576037162
    },
    "GMD": {
      "code": "GMD",
      "value": 74.8800119312
    },
    "GNF": {
      "code": "GNF",
      "value": 8795.0013873732
    },
    "GTQ": {
      "code": "GTQ",
      "value": 7.6430012293
    },
    "GYD": {
      "code": "GYD",
      "value": 208.9800315841
    },
    "HKD": {
      "code": "HKD",
      "value": 7.8363013758
    },
    "HNL": {
      "code": "HNL",
      "value": 26.560904229
    },
    "HRK": {
      "code": "HRK",
      "value": 6.5397415544
    },
    "HTG": {
      "code": "HTG",
      "value": 133.0800231801
    },
    "HUF": {
      "code": "HUF",
      "value": 333.7600396223
    },
    "IDR": {
      "code": "IDR",
      "value": 17014.00317343
    },
    "ILS": {
      "code": "ILS",
      "value": 3.1283005141
    },
    "IMP": {
      "code": "IMP",
      "value": 0.7576037185
    },
    "INR": {
      "code": "INR",
      "value": 92.7000184093
    },
    "IQD": {
      "code": "IQD",
      "value": 1310.5202351811
    },
    "IRR": {
      "code": "IRR",
      "value": 1316384.7552692
    },
    "ISK": {
      "code": "ISK",
      "value": 125.3800130294
    },
    "JEP": {
      "code": "JEP",
      "value": 0.7576036892
    },
    "JMD": {
      "code": "JMD",
      "value": 157.7260194431
    },
    "JOD": {
      "code": "JOD",
      "value": 0.71
    },
    "JPY": {
      "code": "JPY",
      "value": 159.6770264139
    },
    "KES": {
      "code": "KES",
      "value": 129.8148762394
    },
    "KGS": {
      "code": "KGS",
      "value": 87.4500171693
    },
    "KHR": {
      "code": "KHR",
      "value": 4003.0005435431
    },
    "KMF": {
      "code": "KMF",
      "value": 427.0500642269
    },
    "KPW": {
      "code": "KPW",
      "value": 899.9838714433
    },
    "KRW": {
      "code": "KRW",
      "value": 1511.0402107009
    },
    "KWD": {
      "code": "KWD",
      "value": 0.3078000354
    },
    "KYD": {
      "code": "KYD",
      "value": 0.83333
    },
    "KZT": {
      "code": "KZT",
      "value": 470.6900573537
    },
    "LAK": {
      "code": "LAK",
      "value": 21961.003362938
    },
    "LBP": {
      "code": "LBP",
      "value": 89500.012517102
    },
    "LKR": {
      "code": "LKR",
      "value": 315.5000542978
    },
    "LRD": {
      "code": "LRD",
      "value": 183.9820258025
    },
    "LSL": {
      "code": "LSL",
      "value": 16.9551018553
    },
    "LTC": {
      "code": "LTC",
      "value": 0.0187340449
    },
    "LTL": {
      "code": "LTL",
      "value": 2.9969367771
    },
    "LVL": {
      "code": "LVL",
      "value": 0.6100113143
    },
    "LYD": {
      "code": "LYD",
      "value": 6.3932009484
    },
    "MAD": {
      "code": "MAD",
      "value": 9.3907014817
    },
    "MATIC": {
      "code": "MATIC",
      "value": 10.8130296756
    },
    "MDL": {
      "code": "MDL",
      "value": 17.4700020718
    },
    "MGA": {
      "code": "MGA",
      "value": 4180.0008303485
    },
    "MKD": {
      "code": "MKD",
      "value": 53.4200070531
    },
    "MMK": {
      "code": "MMK",
      "value": 2098.6802951651
    },
    "MNT": {
      "code": "MNT",
      "value": 3573.3518564251
    },
    "MOP": {
      "code": "MOP",
      "value": 8.0714014793
    },
    "MRO": {
      "code": "MRO",
      "value": 356.999828
    },
    "MRU": {
      "code": "MRU",
      "value": 39.8797546121
    },
    "MUR": {
      "code": "MUR",
      "value": 46.920008324
    },
    "MVR": {
      "code": "MVR",
      "value": 15.4600018348
    },
    "MWK": {
      "code": "MWK",
      "value": 1733.6732305593
    },
    "MXN": {
      "code": "MXN",
      "value": 17.8813026033
    },
    "MYR": {
      "code": "MYR",
      "value": 4.0310006008
    },
    "MZN": {
      "code": "MZN",
      "value": 63.5400084477
    },
    "NAD": {
      "code": "NAD",
      "value": 16.946201908
    },
    "NGN": {
      "code": "NGN",
      "value": 1378.1501722296
    },
    "NIO": {
      "code": "NIO",
      "value": 36.7864031638
    },
    "NOK": {
      "code": "NOK",
      "value": 9.769861095
    },
    "NPR": {
      "code": "NPR",
      "value": 150.3180212397
    },
    "NZD": {
      "code": "NZD",
      "value": 1.7569002112
    },
    "OMR": {
      "code": "OMR",
      "value": 0.3850000567
    },
    "OP": {
      "code": "OP",
      "value": 9.0723330616
    },
    "PAB": {
      "code": "PAB",
      "value": 1.0000001426
    },
    "PEN": {
      "code": "PEN",
      "value": 3.45280035
    },
    "PGK": {
      "code": "PGK",
      "value": 4.3020008115
    },
    "PHP": {
      "code": "PHP",
      "value": 60.2160080805
    },
    "PKR": {
      "code": "PKR",
      "value": 278.9300504692
    },
    "PLN": {
      "code": "PLN",
      "value": 3.7115304008
    },
    "PYG": {
      "code": "PYG",
      "value": 6450.0010450846
    },
    "QAR": {
      "code": "QAR",
      "value": 3.641000546
    },
    "RON": {
      "code": "RON",
      "value": 4.4266004813
    },
    "RSD": {
      "code": "RSD",
      "value": 101.7620112606
    },
    "RUB": {
      "code": "RUB",
      "value": 79.7000110795
    },
    "RWF": {
      "code": "RWF",
      "value": 1460.610162012
    },
    "SAR": {
      "code": "SAR",
      "value": 3.7549005599
    },
    "SBD": {
      "code": "SBD",
      "value": 8.0625240464
    },
    "SCR": {
      "code": "SCR",
      "value": 15.0450024592
    },
    "SDG": {
      "code": "SDG",
      "value": 601.5
    },
    "SEK": {
      "code": "SEK",
      "value": 9.4827011051
    },
    "SGD": {
      "code": "SGD",
      "value": 1.2874001362
    },
    "SHP": {
      "code": "SHP",
      "value": 0.7566001049
    },
    "SLE": {
      "code": "SLE",
      "value": 22.9101459956
    },
    "SLL": {
      "code": "SLL",
      "value": 22849.003831036
    },
    "SOL": {
      "code": "SOL",
      "value": 0.0124375758
    },
    "SOS": {
      "code": "SOS",
      "value": 570.2501050525
    },
    "SRD": {
      "code": "SRD",
      "value": 37.5600056459
    },
    "STD": {
      "code": "STD",
      "value": 21465.245067671
    },
    "STN": {
      "code": "STN",
      "value": 21.4652448324
    },
    "SVC": {
      "code": "SVC",
      "value": 8.75
    },
    "SYP": {
      "code": "SYP",
      "value": 112.2359640805
    },
    "SZL": {
      "code": "SZL",
      "value": 16.9758024169
    },
    "THB": {
      "code": "THB",
      "value": 32.6700060862
    },
    "TJS": {
      "code": "TJS",
      "value": 9.5863014574
    },
    "TMT": {
      "code": "TMT",
      "value": 3.5
    },
    "TND": {
      "code": "TND",
      "value": 2.9175005739
    },
    "TOP": {
      "code": "TOP",
      "value": 2.3770002604
    },
    "TRX": {
      "code": "TRX",
      "value": 3.165143848
    },
    "TRY": {
      "code": "TRY",
      "value": 44.5856086999
    },
    "TTD": {
      "code": "TTD",
      "value": 6.7227008579
    },
    "TWD": {
      "code": "TWD",
      "value": 32.0290056656
    },
    "TZS": {
      "code": "TZS",
      "value": 2588.0003174368
    },
    "UAH": {
      "code": "UAH",
      "value": 43.9394082022
    },
    "UGX": {
      "code": "UGX",
      "value": 3756.9004866358
    },
    "USD": {
      "code": "USD",
      "value": 1
    },
    "USDC": {
      "code": "USDC",
      "value": 0.9980749913
    },
    "USDT": {
      "code": "USDT",
      "value": 0.9988622579
    },
    "UYU": {
      "code": "UYU",
      "value": 40.5880045637
    },
    "UZS": {
      "code": "UZS",
      "value": 12170.672185045
    },
    "VEF": {
      "code": "VEF",
      "value": 47295002.061675
    },
    "VES": {
      "code": "VES",
      "value": 472.9500421152
    },
    "VND": {
      "code": "VND",
      "value": 26323.004462061
    },
    "VUV": {
      "code": "VUV",
      "value": 119.3391052734
    },
    "WST": {
      "code": "WST",
      "value": 2.7662779532
    },
    "XAF": {
      "code": "XAF",
      "value": 569.4801100494
    },
    "XAG": {
      "code": "XAG",
      "value": 0.0136969738
    },
    "XAU": {
      "code": "XAU",
      "value": 0.0002138383
    },
    "XCD": {
      "code": "XCD",
      "value": 2.7
    },
    "XCG": {
      "code": "XCG",
      "value": 1.7973038184
    },
    "XDR": {
      "code": "XDR",
      "value": 0.7249801422
    },
    "XOF": {
      "code": "XOF",
      "value": 569.4801013175
    },
    "XPD": {
      "code": "XPD",
      "value": 0.0006633582
    },
    "XPF": {
      "code": "XPF",
      "value": 103.6500113668
    },
    "XPT": {
      "code": "XPT",
      "value": 0.0005042896
    },
    "XRP": {
      "code": "XRP",
      "value": 0.7585055133
    },
    "YER": {
      "code": "YER",
      "value": 238.5700244331
    },
    "ZAR": {
      "code": "ZAR",
      "value": 16.9300026288
    },
    "ZMK": {
      "code": "ZMK",
      "value": 9001.2
    },
    "ZMW": {
      "code": "ZMW",
      "value": 19.2500029495
    },
    "ZWG": {
      "code": "ZWG",
      "value": 25.3571208251
    },
    "ZWL": {
      "code": "ZWL",
      "value": 63360.446761529
    }
  }
}